dynamikontrol/BaseLED.py
dynamikontrol/LED.py
dynamikontrol/Module.py
dynamikontrol/Motor.py
dynamikontrol/Protocol.py
dynamikontrol/Switch.py
dynamikontrol/Timer.py
dynamikontrol/__init__.py
dynamikontrol/helpers/__init__.py
dynamikontrol/helpers/helper.py
DynamiKontrol-0.5.0.dist-info/LICENSE.txt
DynamiKontrol-0.5.0.dist-info/METADATA
DynamiKontrol-0.5.0.dist-info/WHEEL
DynamiKontrol-0.5.0.dist-info/top_level.txt
DynamiKontrol-0.5.0.dist-info/RECORD
