Metadata-Version: 2.1
Name: DynamiKontrol
Version: 0.5.0
Summary: DynamiKontrol Python API
Home-page: https://github.com/TheMatrixGroup/DynamiKontrol
Author: Taehee Lee
Author-email: kairess87@gmail.com
License: MIT
Platform: UNKNOWN
Classifier: Programming Language :: Python :: 3
Classifier: License :: OSI Approved :: MIT License
Classifier: Operating System :: OS Independent
Classifier: Topic :: System :: Hardware
Classifier: Topic :: System :: Hardware :: Hardware Drivers
Requires-Python: >=3.4.2
License-File: LICENSE.txt
